{
  "DarkPiano": "Piano Gelap",
  "OakChair": "Kursi Oak",
  "WalnutChair": "Kursi Kenari",
  "BirchChair": "Kursi Birch",
  "MahoganyChair": "Kursi Mahoni",
  "RedDinerChair": "Kursi Makan Merah",
  "BlueDinerChair": "Kursi Makan Biru",
  "CountryChair": "Kursi Desa",
  "BreakfastChair": "Kursi Sarapan",
  "PinkOfficeChair": "Kursi Kantor Merah Muda",
  "PurpleOfficeChair": "Kursi Kantor Ungu",
  "GreenOfficeStool": "Kursi Kantor Hijau",
  "OrangeOfficeStool": "Kursi Kantor Oranye",
  "DarkThrone": "Singgasana Gelap",
  "DiningChair": "Kursi Makan",
  "GreenPlushSeat": "Kursi Empuk Hijau",
  "PinkPlushSeat": "Kursi Empuk Merah Muda",
  "WinterChair": "Kursi Musim Dingin",
  "GroovyChair": "Kursi Ikonik",
  "CuteChair": "Kursi Lucu",
  "StumpSeat": "Kursi Tunggul",
  "MetalChair": "Kursi Logam",
  "GreenStool": "Bangku Hijau",
  "BlueStool": "Bangku Biru",
  "KingChair": "Kursi Raja",
  "CrystalChair": "Kursi Kristal",
  "OakBench": "Bangku Oak",
  "WalnutBench": "Bangku Kenari",
  "BirchBench": "Bangku Birch",
  "MahoganyBench": "Bangku Mahoni",
  "ModernBench": "Bangku Modern",
  "BlueArmchair": "Sofa Berlengan Biru",
  "RedArmchair": "Sofa Berlengan Merah",
  "GreenArmchair": "Sofa Berlengan Hijau",
  "YellowArmchair": "Sofa Berlengan Kuning",
  "BrownArmchair": "Sofa Berlengan Coklat",
  "BlueCouch": "Sofa Biru",
  "RedCouch": "Sofa Merah",
  "GreenCouch": "Sofa Hijau",
  "YellowCouch": "Sofa Kuning",
  "BrownCouch": "Sofa Cokelat",
  "DarkCouch": "Sofa Gelap",
  "WizardCouch": "Sofa Penyihir",
  "WoodsyCouch": "Sofa Kayu",
  "OakDresser": "Laci Pakaian Oak",
  "WalnutDresser": "Laci Pakaian Kenari",
  "BirchDresser": "Laci Pakaian Birch",
  "MahoganyDresser": "Laci Pakaian Mahoni",
  "CoffeeTable": "Meja Kopi",
  "StoneSlab": "Lempengan Batu",
  "WinterDiningTable": "Meja Makan Musim Dingin",
  "FestiveDiningTable": "Meja Makan Meriah",
  "MahoganyDiningTable": "Meja Makan Mahoni",
  "ModernDiningTable": "Meja Makan Modern",
  "OakTable": "Meja Oak",
  "WalnutTable": "Meja Kenari",
  "BirchTable": "Meja Birch",
  "MahoganyTable": "Meja Mahoni",
  "SunTable": "Meja Matahari",
  "MoonTable": "Meja Bulan",
  "ModernTable": "Meja Modern",
  "PubTable": "Meja Pub",
  "LuxuryTable": "Meja Mewah",
  "DivinerTable": "Meja Peramal",
  "NeolithicTable": "Meja Neolitikum",
  "PuzzleTable": "Meja Puzzle",
  "WinterTable": "Meja Musim Dingin",
  "CandyTable": "Meja Permen",
  "LuauTable": "Meja Luau",
  "DarkTable": "Meja Gelap",
  "OakTeaTable": "Meja Lesehan Oak",
  "WalnutTeaTable": "Meja Lesehan Kenari",
  "BirchTeaTable": "Meja Lesehan Birch",
  "MahoganyTeaTable": "Meja Lesehan Mahoni",
  "ModernTeaTable": "Meja Lesehan Modern",
  "FurnitureCatalogue": "Katalog Furnitur",
  "ChinaCabinet": "Bufet Porselen",
  "ArtistBookcase": "Rak Buku Seniman",
  "LuxuryBookcase": "Rak Buku Mewah",
  "ModernBookcase": "Rak Buku Modern",
  "DarkBookcase": "Rak Buku Gelap",
  "CeramicPillar": "Pilar Keramik",
  "GoldPillar": "Pilar Emas",
  "IndustrialPipe": "Pipa Industri",
  "IndoorPalm": "Palem Dalam Ruangan",
  "TotemPole": "Tiang Totem",
  "ManicuredPine": "Pinus Terawat",
  "TopiaryTree": "Pohon Topiari",
  "StandingGeode": "Geoda Berdiri",
  "ObsidianVase": "Vas Obsidian",
  "SingingStone": "Batu Bernyanyi",
  "SlothSkeletonL": "Kerangka Kungkang (ki)",
  "SlothSkeletonM": "Kerangka Kungkang (te)",
  "SlothSkeletonR": "Kerangka Kungkang (ka)",
  "Skeleton": "Kerangka",
  "ChickenStatue": "Patung Ayam",
  "LeahsSculpture": "Pahatan Leah",
  "DriedSunflowers": "Bunga Matahari Kering",
  "Catalogue": "Katalog",
  "SamsBoombox": "Pemutar Kaset Sam",
  "SmallPlant": "Tanaman Kecil",
  "TablePlant": "Tanaman Meja",
  "DecorativeBowl": "Mangkuk Hias",
  "FutanBear": "Boneka Beruang",
  "Globe": "Bola Dunia",
  "ModelShip": "Model Kapal",
  "SmallCrystal": "Kristal Kecil",
  "DecorativeLantern": "Lentera Hias",
  "HousePlant": "Tanaman Rumah",
  "OakEndTable": "Meja Sudut Oak",
  "WalnutEndTable": "Meja Sudut Kenari",
  "BirchEndTable": "Meja Sudut Birch",
  "MahoganyEndTable": "Meja Sudut Mahoni",
  "ModernEndTable": "Meja Sudut Modern",
  "GrandmotherEndTable": "Meja Sudut Nenek",
  "WinterEndTable": "Meja Sudut Musim Dingin",
  "Calendar": "Kalender",
  "TreeoftheWinterStar": "Pohon Bintang-Musim-Dingin",
  "CountryLamp": "Lampu Desa",
  "BoxLamp": "Lampu Kotak",
  "ModernLamp": "Lampu Modern",
  "ClassicLamp": "Lampu Klasik",
  "RedRug": "Karpet Merah",
  "PatchworkRug": "Karpet Kain Perca",
  "DarkRug": "Karpet Gelap",
  "BudgetTV": "TV Tabung",
  "PlasmaTV": "TV Plasma",
  "TheMuzzamaroo": "\"Sang Muzzamaroo\"",
  "ANightOnEcoHill": "\"Malam di Bukit Ramah Lingkungan\"",
  "Pathways": "\"Jalur Setapak\"",
  "BurntOffering": "\"Persembahan yang Terbakar\"",
  "QueenoftheGemSea": "\"Ratu Laut Permata\"",
  "VanillaVilla": "\"Villa Vanilla\"",
  "PrimalMotion": "\"Gerakan Purba\"",
  "JadeHills": "\"Bukit Giok\"",
  "Sun44": "\"Matahari #44\"",
  "WallflowerPal": "Sahabat Hiasan Dinding",
  "Spires": "\"Menara\"",
  "Highway89": "\"Jalan Raya 89\"",
  "CalicoFalls": "Air Terjun Calico",
  "NeedlepointFlower": "Bunga Sulaman",
  "SkullPoster": "Poster Tengkorak",
  "Sun45": "\"Matahari #45\"",
  "LittleTree": "\"Pohon Kecil\"",
  "Blueberries": "\"Bluberi\"",
  "BlueCity": "\"Kota Biru\"",
  "LittlePhotos": "Foto-Foto Kecil",
  "DancingGrass": "\"Rumput Menari\"",
  "VGAParadise": "\"Surga VGA\"",
  "JColaLight": "Plang J. Cola",
  "Kitemaster95": "\"Ahli Layangan '95\"",
  "BasicWindow": "Jendela Biasa",
  "SmallWindow": "Jendela Kecil",
  "RedCottageRug": "Karpet Penginapan Merah",
  "GreenCottageRug": "Karpet Penginapan Hijau",
  "MonsterRug": "Karpet Monster",
  "BoardedWindow": "Jendela Bertingkat",
  "MysticRug": "Karpet Mistik",
  "LgFutanBear": "Boneka Beruang Besar",
  "JunimoPlush": "Boneka Junimo",
  "BearStatue": "Patung Beruang",
  "Porthole": "Jendela Kapal",
  "Anchor": "Jangkar",
  "WorldMap": "Peta Dunia",
  "OrnateWindow": "Jendela Berhias",
  "FloorTV": "TV Lantai",
  "CarvedWindow": "Jendela Berukir",
  "NauticalRug": "Karpet Bahari",
  "BurlapRug": "Karpet Goni",
  "TreeColumn": "Kolom Pohon",
  "LLightString": "Untaian Lampu Kecil",
  "SPine": "Pinus Kecil",
  "BonsaiTree": "Pohon Bonsai",
  "MetalWindow": "Jendela Logam",
  "CandleLamp": "Lampu Lilin",
  "MinersCrest": "Lambang Penambang",
  "BambooMat": "Tikar Bambu",
  "OrnateLamp": "Lampu Hiasan",
  "WoodcutRug": "Karpet Ukiran Kayu",
  "HangingShield": "Perisai Gantung",
  "MonsterDanglers": "Gantungan Monster",
  "CeilingFlags": "Bendera Langit-langit",
  "RedEagle": "\"Elang Merah\"",
  "PortraitOfAMermaid": "\"Potret Putri Duyung\"",
  "SolarKingdom": "\"Kerajaan Matahari\"",
  "Clouds": "\"Awan\"",
  "1000YearsFromNow": "\"1000 Tahun Dari Sekarang\"",
  "ThreeTrees": "\"Tiga Pohon\"",
  "TheSerpent": "\"Sang Ular\"",
  "TropicalFish173": "\"Ikan Tropis #173\"",
  "LandOfClay": "\"Negeri Tanah Liat\"",
  "BrickFireplace": "Perapian Bata",
  "StoneFireplace": "Perapian Batu",
  "IridiumFireplace": "Perapian Iridium",
  "StoveFireplace": "Perapian Tungku",
  "MonsterFireplace": "Perapian Monster",
  "MyFirstPainting": "Lukisan Pertamaku",
  "ElegantFireplace": "Perapian Elegan",
  "PirateFlag": "Bendera Bajak Laut",
  "PirateRug": "Karpet Bajak Laut",
  "BoneRug": "Karpet Tulang",
  "ButterflyHutch": "Sangkar Kupu-Kupu",
  "StrawberryDecal": "Stiker Stroberi",
  "FruitSaladRug": "Karpet Buah-Buahan",
  "NightSkyDecal1": "Stiker Langit Malam #1",
  "SnowyRug": "Karpet Bersalju",
  "NightSkyDecal2": "Stiker Langit Malam #2",
  "NightSkyDecal3": "Stiker Langit Malam #3",
  "TheBraveLittleSapling": "\"Bibit Pohon Kecil yang Pemberani\"",
  "Mysterium": "\"Misterium\"",
  "JourneyOfThePrairieKingTheMotionPicture": "\"Perjalanan Sang Raja Prairi: Sinema Layar Lebar\"",
  "Wumbus": "\"Wumbus\"",
  "TheZuzuCityExpress": "\"Kereta Ekspres Kota Zuzu\"",
  "TheMiracleAtColdstarRanch": "\"Keajaiban di Peternakan Coldstar\"",
  "NaturalWondersExploringOurVibrantWorld": "\"Keajaiban Alam: Menjelajahi Dunia Kita yang Penuh Warna\"",
  "ItHowlsInTheRain": "\"Ia Melolong di Tengah Hujan\"",
  "IndoorHangingBasket": "Keranjang Gantung Dalam Ruangan",
  "WinterTreeDecal": "Stiker Pohon Musim Dingin",
  "SmallJunimoPlush": "Boneka Junimo Kecil",
  "FutanRabbit": "Boneka Kelinci",
  "WumbusStatue": "Patung Wumbus",
  "BoboStatue": "Patung Bobo",
  "PurpleSerpentStatue": "Patung Ular Ungu",
  "GreenSerpentStatue": "Patung Ular Hijau",
  "LongPalm": "Palem Panjang",
  "LongCactus": "Kaktus Panjang",
  "ExoticTree": "Pohon Eksotis",
  "DeluxeTree": "Pohon Premium",
  "WallPumpkin": "Labu Dinding",
  "SmallWallPumpkin": "Labu Dinding Kecil",
  "Bed": "Ranjang",
  "DoubleBed": "Ranjang Ganda",
  "StarryDoubleBed": "Ranjang Ganda Berbintang",
  "StrawberryDoubleBed": "Ranjang Ganda Stroberi",
  "PirateDoubleBed": "Ranjang Ganda Bajak Laut",
  "ChildBed": "Ranjang Anak",
  "TropicalBed": "Ranjang Tropis",
  "TropicalDoubleBed": "Ranjang Ganda Tropis",
  "DeluxeRedDoubleBed": "Ranjang Ganda Merah Premium",
  "ModernDoubleBed": "Ranjang Ganda Modern",
  "LargeFishTank": "Akuarium Besar",
  "DeluxeFishTank": "Akuarium Premium",
  "SmallFishTank": "Akuarium Kecil",
  "OceanicRug": "Karpet Samudra",
  "TropicalTV": "TV Tropis",
  "VolcanoPhoto": "Foto \"Gunung Berapi\"",
  "JungleTorch": "Obor Hutan",
  "PalmWallOrnament": "Ornamen Dinding Palem",
  "TropicalChair": "Kursi Tropis",
  "AquaticSanctuary": "Suaka Akuatik",
  "ModernFishTank": "Akuarium Modern",
  "WildDoubleBed": "Ranjang Ganda Liar",
  "FisherDoubleBed": "Ranjang Ganda Nelayan",
  "BirchDoubleBed": "Ranjang Ganda Birch",
  "ExoticDoubleBed": "Ranjang Ganda Eksotis",
  "Lifesaver": "Pelampung",
  "FoliagePrint": "Cetakan Dedaunan",
  "Boat": "\"Perahu\"",
  "Vista": "\"Vista\"",
  "WallBasket": "Keranjang Dinding",
  "DecorativeTrashCan": "Tempat Sampah Hias",
  "IridiumKrobus": "Krobus Iridium",
  "GourmandStatue": "Patung Gourmand",
  "PyramidDecal": "Stiker Piramida",
  "PlainTorch": "Obor Biasa",
  "StumpTorch": "Obor Tunggul",
  "WallFlower": "Bunga Dinding",
  "SWallFlower": "Bunga Dinding Kecil",
  "CloudsBanner": "Spanduk Awan",
  "ColorfulSet": "Rangkaian Warna-Warni",
  "PastelBanner": "Spanduk Pastel",
  "WinterBanner": "Spanduk Musim Dingin",
  "MoonlightJelliesBanner": "Spanduk Ubur-Ubur Moonlight",
  "JungleDecal": "Stiker Hutan",
  "StarportDecal": "Stiker Starport",
  "DecorativePitchfork": "Garpu-Rumput Hias",
  "WoodPanel": "Panel Kayu",
  "DecorativeAxe": "Kapak Hias",
  "LogPanel": "Panel Kayu Batangan",
  "CeilingLeaves": "Daun Langit-Langit",
  "CloudDecal": "Stiker Awan",
  "FloorDividerR": "Pembatas Lantai (ka)",
  "FloorDividerL": "Pembatas Lantai (ki)",
  "LightGreenRug": "Karpet Hijau Muda",
  "JadeHillsExtended": "\"Bukit Giok Panjang\"",
  "LargeBrownCouch": "Sofa Besar Cokelat",
  "LargeGreenRug": "Karpet Hijau Besar",
  "IcyRug": "Karpet Es",
  "OldWorldRug": "Karpet Dunia Lama",
  "LargeRedRug": "Karpet Merah Besar",
  "FrozenDreams": "\"Mimpi Beku\"",
  "IcyBanner": "Spanduk Es",
  "WallPalm": "Palem Dinding",
  "WallCactus": "Kaktus Dinding",
  "LargeCottageRug": "Karpet Penginapan Besar",
  "Physics101": "\"Fisika 101\"",
  "WallSconce": "Tempat lilin dinding",
  "BlossomRug": "Karpet Bunga",
  "FunkyRug": "Karpet Unik",
  "ModernRug": "Karpet Modern",
  "SquirrelFigurine": "Patung Tupai",
  "Cactus": "Kaktus",
  "HangingFish": "Ikan Gantung",
  "RetroTV": "TV Retro",
  "ArtPhoto": "Foto Seni",
  "ArtPhoto2": "Foto Seni 2",
  "ShortBookcase": "Rak Buku Pendek",
  "PierresSign": "Penanda Pierre",
  "SamsSkateboard": "Papan Luncur Sam",
  "ChickenDecal": "Stiker Ayam",
  "ExoticPalace": "Istana Eksotis",
  "PeriodicTable": "Tabel Periodik",
  "DustySkull": "Tengkorak Berdebu",
  "RadioDesk": "Meja Radio",
  "ModelPlanes": "Model Pesawat",
  "CalicoStatue": "Patung Calico",
  "SunDunes": "Bukit-Pasir Matahari",
  "DesertTable": "Meja Gurun",
  "DesertChair": "Kursi Gurun",
  "DesertFireplace": "Perapian Gurun",
  "SandyRug": "Karpet Berpasir",
  "DesertRug": "Karpet Gurun",
  "DesertEndTable": "Meja Sudut Gurun",
  "DesertFlags": "Bendera Gurun",
  "DecorativeBarrel": "Laras Dekoratif",
  "MountedTrout": "Ikan Trout yang Dipasang",
  "SquidKid": "\"Bocah Cumi-Cumi\"",
  "CowDecal": "Stiker Sapi",
  "BluePinstripeBed": "Ranjang Bergaris Biru",
  "JungleTank": "Akuarium Hutan",
  "CCFishTank": "AkuariumBD",
  "BluePinstripeDoubleBed": "Ranjang Ganda Bergaris Biru",
  "JojaBed": "Ranjang Joja",
  "JojaVault": "Lemari Besi Joja",
  "JojaChair": "Kursi Joja",
  "J": "J",
  "JojaColaTeaTable": "Meja Lesehan Joja Cola",
  "JojaTable": "Meja Joja",
  "JPainting": "Lukisan J.",
  "JLight": "Lampu Hias J.",
  "JojaCatalogue": "Katalog Furnitur Joja",
  "JojaColaPainting": "Lukisan Joja Cola",
  "JojaColaOrnament": "Ornamen Joja Cola",
  "JojaFireplace": "Perapian Joja",
  "JojaColaCans": "Kaleng Joja Cola",
  "CashRegister": "Mesin Kasir",
  "PlasticPlant": "Tanaman Plastik",
  "PlasticSapling": "Bibit Pohon Plastik",
  "GrayJojaCushion": "Bantal Joja Abu-Abu",
  "JojaCushion": "Bantal Joja",
  "StackedJojaBoxes": "Tumpukan Kardus Joja",
  "JojaCouch": "Sofa Joja",
  "MorrisPortrait": "Manajer Tahun Ini",
  "JojaHQPainting": "Lukisan Kantor Pusat Joja",
  "JojaCrate": "Peti Joja",
  "JojaShoppingCart": "Keranjang Belanja Joja",
  "LargeJojaCrate": "Peti Joja Besar",
  "JojaColaFridge": "Kulkas Joja Cola",
  "JojaDresser": "Laci Pakaian Joja",
  "GrayJojaDresser": "Laci Pakaian Abu-Abu Joja",
  "LargeJojaRug": "Karpet Joja Besar",
  "SmallJojaRug": "Karpet Joja Kecil",
  "SquareJojaRug": "Karpet Joja Persegi",
  "JojaRug": "Karpet Joja",
  "JojaCoffeeTable": "Karpet Joja",
  "GrayJojaCoffeeTable": "Meja Kopi Joja Abu-Abu",
  "JojaLamp": "Lampu Joja",
  "GrayJojaBookcase": "Rak Buku Joja Abu-Abu",
  "JojaBookcase": "Rak Buku Joja",
  "JojaStool": "Bangku Joja",
  "JojaEndTable": "Meja Sudut Joja",
  "GrayJojaEndTable": "Meja Sudut Joja Abu-Abu",
  "DecorativeJojaDoor": "Pintu Dekoratif Joja",
  "WizardBed": "Ranjang Penyihir",
  "LargeWizardBookcase": "Rak Buku Penyihir Besar",
  "WizardBookcase": "Rak Buku Penyihir",
  "ShortWizardBookcase": "Rak Buku Penyihir Pendek",
  "SmallWizardBookcase": "Rak Buku Penyihir Kecil",
  "WizardStool": "Bangku Penyihir",
  "WizardFireplace": "Perapian Penyihir",
  "WizardDresser": "Laci Pakaian Penyihir",
  "WizardStudy": "Tempat Belajar Penyihir",
  "WizardEndTable": "Meja Sudut Penyihir",
  "WitchBroom": "Sapu Nenek Sihir",
  "Cauldron": "Kuali",
  "CurlyTree": "Pohon Keriting",
  "LeafyPlant": "Tanaman Rawa",
  "WizardChair": "Kursi Penyihir",
  "WizardTable": "Meja Penyihir",
  "WizardCushion": "Bantal Penyihir",
  "DarkWizardCushion": "Bantal Penyihir Gelap",
  "WizardTeaTable": "Meja Lesehan Penyihir",
  "SmallElixirShelf": "Rak Ramuan Kecil",
  "ElixirShelf": "Rak Ramuan",
  "SmallStackedElixirShelf": "Rak Ramuan Bertumpuk Kecil",
  "StackedElixirShelf": "Rak Ramuan Bertumpuk",
  "ElixirBundle": "Bundel Ramuan",
  "CoupleElixirs": "Sepasang Ramuan",
  "ElixirTable": "Meja Ramuan",
  "LongElixirTable": "Meja Ramuan Panjang",
  "WizardLamp": "Lampu Penyihir",
  "Runes": "\"Mantra\"",
  "WizardTower": "\"Menara Penyihir\"",
  "PottedRedMushroom": "Jamur Merah dalam Pot",
  "WizardCatalogue": "Katalog Penyihir",
  "VoidSwirls": "\"Pusaran Hampa\"",
  "WizardBookshelf": "Rak Buku Penyihir",
  "Glyph": "Rajah",
  "StoneFlooring": "Lantai Batu",
  "RuneRug": "Karpet Rune",
  "SwirlRug": "Karpet Pusaran",
  "StarryMoonRug": "Karpet Bulan Berbintang",
  "CrystalBall": "Bola Kristal",
  "AmethystCrystalBall": "Bola Kristal Kecubung",
  "TopazCrystalBall": "Bola Kristal Topas",
  "AquamarineCrystalBall": "Bola Kristal Akuamarin",
  "EmeraldCrystalBall": "Bola Kristal Zamrud",
  "RubyCrystalBall": "Bola Kristal Mirah",
  "SmallBookStack": "Susunan Buku Kecil",
  "BookStack": "Susunan Buku",
  "LargeBookStack": "Susunan Buku Besar",
  "PurpleBook": "Buku Ungu",
  "BlueBook": "Buku Biru",
  "YellowBook": "Buku Kuning",
  "RedBook": "Buku Merah",
  "GreenBook": "Buku Hijau",
  "BrownBook": "Buku Cokelat",
  "FallenPurpleBook": "Buku Ungu yang Jatuh",
  "FallenBlueBook": "Buku Biru yang Jatuh",
  "FallenYellowBook": "Buku Kuning yang Jatuh",
  "FallenRedBook": "Buku Merah yang Jatuh",
  "FallenGreenBook": "Buku Hijau yang Jatuh",
  "FallenBrownBook": "Buku Cokelat yang Jatuh",
  "SmallBookPile": "Tumpukan Buku Kecil",
  "BookPile": "Tumpukan Buku",
  "LargeBookPile": "Tumpukan Buku Besar",
  "DecorativeWizardDoor": "Pintu Dekoratif Penyihir",
  "JunimoBed": "Ranjang Junimo",
  "JunimoHut": "Gubuk Junimo",
  "LargeJunimoHut": "Gubuk Junimo Besar",
  "SmallJunimoHut": "Gubuk Junimo Kecil",
  "JunimoFireplace": "Perapian Junimo",
  "JunimoBookcase": "Rak Buku Junimo",
  "JunimoPot": "Pot Junimo",
  "JunimoBag": "Kantong Junimo",
  "JunimoBundle": "Bundel Junimo",
  "JunimoStool": "Bangku Junimo",
  "JunimoTable": "Meja Junimo",
  "JunimoChair": "Kursi Junimo",
  "SmallJunimoPot": "Pot Junimo Kecil",
  "JunimoFlower": "Bunga Junimo",
  "JunimoEndTable": "Meja Sudut Junimo",
  "JunimoCatalogue": "Katalog Junimo",
  "JunimoTeaTable": "Meja Lesehan Junimo",
  "JunimoDresser": "Laci Pakaian Junimo",
  "JunimoLamp": "Lampu Junimo",
  "JunimoPlant": "Tanaman Junimo",
  "JunimoWallPlaque": "Plakat Dinding Junimo",
  "JunimoPlaque": "Plakat Junimo",
  "JunimoCushion": "Bantal Junimo",
  "DarkJunimoCushion": "Bantal Junimo Gelap",
  "JunimoTree": "Pohon Junimo",
  "JunimoCouch": "Sofa Junimo",
  "GreenSleepingJunimo": "Junimo Hijau Tidur",
  "BlueSleepingJunimo": "Junimo Biru Tidur",
  "RedSleepingJunimo": "Junimo Merah Tidur",
  "PurpleSleepingJunimo": "Junimo Ungu Tidur",
  "YellowSleepingJunimo": "Junimo Kuning Tidur",
  "OrangeSleepingJunimo": "Junimo Oranye Tidur",
  "GraySleepingJunimo": "Junimo Abu-Abu Tidur",
  "SquareJunimoRug": "Karpet Junimo Persegi",
  "JunimoRug": "Karpet Junimo",
  "JunimoMat": "Keset Junimo",
  "CircularJunimoRug": "Karpet Junimo Bundar",
  "SmallJunimoMat": "Keset Junimo Kecil",
  "CommunityCenter": "\"Balai Desa\"",
  "LittleBuddies": "\"Teman-Teman Kecil\"",
  "Stardrop": "\"Stardrop\"",
  "Hut": "\"Gubuk\"",
  "AbigailPortrait": "Potret Abigail",
  "EmilyPortrait": "Potret Emily",
  "HaleyPortrait": "Potret Haley",
  "LeahPortrait": "Potret Leah",
  "MaruPortrait": "Potret Maru",
  "PennyPortrait": "Potret Penny",
  "AlexPortrait": "Potret Alex",
  "ElliottPortrait": "Potret Elliott",
  "HarveyPortrait": "Potret Harvey",
  "SamPortrait": "Potret Sam",
  "SebastianPortrait": "Potret Sebastian",
  "ShanePortrait": "Potret Shane",
  "KrobusPortrait": "Potret Krobus",
  "JunimoStar": "Bintang Junimo",
  "BulletinBoard": "Papan Buletin",
  "BrochureCabinet": "Rak Brosur",
  "LeafyWallPanel": "Panel Dinding Berdaun",
  "LightLeafyWallPanel": "Panel Dinding Berdaun Cerah",
  "DarkLeafyWallPanel": "Panel Dinding Berdaun Gelap",
  "DecorativeJunimoDoor": "Pintu Dekoratif Junimo",
  "RetroBed": "Ranjang Retro",
  "RetroDresser": "Meja Sudut Retro",
  "RetroBookcase": "Rak Buku Retro",
  "RetroFireplace": "Perapian Retro",
  "RetroCouch": "Sofa Retro",
  "RetroCushion": "Bantal Retro",
  "DarkRetroCushion": "Bantal Retro Gelap",
  "RetroStool": "Bangku Retro",
  "RetroFlower": "Bunga Retro",
  "RetroChair": "Kursi Retro",
  "RetroTable": "Meja Retro",
  "RetroPlant": "Tanaman Retro",
  "RetroEndTable": "Meja Sudut Retro",
  "RetroTeaTable": "Meja Lesehan Retro",
  "RetroCatalogue": "Katalog Retro",
  "RetroCabinet": "Bufet Retro",
  "RetroRadio": "Radio Retro",
  "RetroBanner": "Spanduk Retro",
  "Groovy": "\"Asyik\"",
  "RetroLamp": "Lampu Retro",
  "RetroRug": "Karpet Retro",
  "RetroSquareRug": "Karpet Persegi Retro",
  "RetroMat": "Keset Retro",
  "LargeRetroRug": "Karpet Retro Besar",
  "Abstract": "\"Abstrak\"",
  "Starship": "\"Kapal Luar Angkasa\"",
  "Binary": "\"Biner\"",
  "Checkers": "\"Catur\"",
  "UFO": "\"UFO\"",
  "DecorativeRetroDoor": "Pintu Dekoratif Retro",
  "DecorativeDoor1": "Pintu Hias",
  "DecorativeDoor2": "Pintu Hias",
  "DecorativeDoor3": "Pintu Hias",
  "DecorativeDoor4": "Pintu Hias",
  "DecorativeDoor5": "Pintu Hias",
  "DecorativeDoor6": "Pintu Hias",
  "WallClock": "Jam Dinding",
  "DecorativeHatch": "Palka Hias",
  "DecorativeOakLadder": "Tangga Oak Hias",
  "DecorativeWalnutLadder": "Tangga Kenari Hias",
  "UprightPiano": "Piano Tegak",
  "CoatStand": "Tempat Mantel",
  "BirdHouse": "Sangkar Burung",
  "DecorativeShovel": "Sekop Hias",
  "WallSword": "Pedang Dinding",
  "DecorativeSword": "Pedang Hias",
  "WineTable": "Meja Anggur",
  "SpiritsTable": "Meja Arwah",
  "TallHousePlant": "Tanaman Rumah Tinggi",
  "CornPlant": "Tanaman Jagung",
  "BlueCushion": "Bantal Biru",
  "YellowCushion": "Bantal Kuning",
  "GreenCushion": "Bantal Hijau",
  "RedCushion": "Bantal Merah",
  "BrownCushion": "Bantal Cokelat",
  "BlackCushion": "Bantal Hitam",
  "FoodPetBowl": "Mangkuk Makan Peliharaan",
  "WaterPetBowl": "Mangkuk Air Peliharaan",
  "OakLampEndTable": "Meja Lampu Oak",
  "WalnutLampEndTable": "Meja Lampu Kenari",
  "BirchLampEndTable": "Meja Lampu Birch",
  "MahoganyLampEndTable": "Meja Lampu Mahoni",
  "TriangleWindow": "Jendela Segitiga",
  "Clothesline": "Jemuran Pakaian",
  "TrashCatalogue": "Katalog Sampah",
  "ElegantVase": "Vas Elegan",
  "CatTree": "Pohon Kucing",
  "DarkCatTree": "Pohon Kucing Gelap",
  "LightSwitch": "Sakelar Lampu",
  "Outlet": "Stopkontak",
  "Doghouse": "Rumah Anjing",
  "DarkDoghouse": "Rumah Anjing Gelap",
  "BountifulDiningTable": "Meja Makan Berlimpah",
  "PlasticLawnEndTable": "Meja-Sudut-Teras Plastik",
  "PlasticLawnChair": "Kursi-Teras Plastik",
  "BrokenTelevision": "TV Rusak",
  "SixPackRings": "Cincin Pengikat Kaleng",
  "GreenBottle": "Botol Hijau",
  "PlasticBag": "Kantong Plastik",
  "AluminumCan": "Kaleng Aluminium",
  "BlueBottle": "Botol Biru",
  "BuriedTire": "Ban yang Terkubur",
  "Tire": "Ban",
  "Wrapper": "Bungkus",
  "SpilledBeverage": "Minuman Tumpah",
  "MessyShirt": "Kemeja Berantakan",
  "MessyShorts": "Celana Pendek Berantakan",
  "MoldyCouch": "Sofa Berjamur",
  "FancyHousePlant": "Tanaman Rumah Mewah",
  "PigPainting": "Lukisan Babi",
  "MidnightBed": "Ranjang Pantai Tengah Malam",
  "MidnightDoubleBed": "Ranjang Ganda Pantai Tengah Malam"
}
